{"latestDate":"2026-02-02","results":{"loto3Cang":{"top10":[{"number":"662","appearances":27,"lastDate":"2025-12-13","daysSinceLastAppearance":51,"averageCycle":16,"maxGan":50,"isDue":true,"hitDates":["2025-10-01","2025-10-16","2025-12-05","2025-12-12","2025-12-13"]},{"number":"053","appearances":26,"lastDate":"2026-01-19","daysSinceLastAppearance":14,"averageCycle":19,"maxGan":70,"isDue":false,"hitDates":["2025-11-17","2025-11-22","2025-12-17","2025-12-22","2026-01-19"]},{"number":"158","appearances":25,"lastDate":"2026-01-12","daysSinceLastAppearance":21,"averageCycle":18,"maxGan":80,"isDue":true,"hitDates":["2025-10-25","2025-11-22","2025-11-27","2025-12-16","2026-01-12"]},{"number":"875","appearances":23,"lastDate":"2026-01-29","daysSinceLastAppearance":4,"averageCycle":22,"maxGan":96,"isDue":false,"hitDates":["2025-07-28","2025-09-25","2025-10-13","2026-01-17","2026-01-29"]},{"number":"978","appearances":22,"lastDate":"2026-01-14","daysSinceLastAppearance":19,"averageCycle":22,"maxGan":76,"isDue":false,"hitDates":["2025-08-17","2025-08-20","2025-11-04","2025-12-12","2026-01-14"]},{"number":"370","appearances":22,"lastDate":"2026-01-09","daysSinceLastAppearance":24,"averageCycle":21,"maxGan":106,"isDue":true,"hitDates":["2025-11-03","2025-11-12","2025-11-17","2025-12-09","2026-01-09"]},{"number":"905","appearances":21,"lastDate":"2025-12-28","daysSinceLastAppearance":36,"averageCycle":23,"maxGan":66,"isDue":true,"hitDates":["2025-08-25","2025-10-14","2025-10-29","2025-12-07","2025-12-28"]},{"number":"634","appearances":21,"lastDate":"2026-01-18","daysSinceLastAppearance":15,"averageCycle":23,"maxGan":86,"isDue":false,"hitDates":["2025-10-07","2025-10-28","2026-01-01","2026-01-04","2026-01-18"]},{"number":"274","appearances":21,"lastDate":"2026-01-05","daysSinceLastAppearance":28,"averageCycle":23,"maxGan":60,"isDue":true,"hitDates":["2025-09-18","2025-09-20","2025-10-22","2025-11-20","2026-01-05"]},{"number":"139","appearances":21,"lastDate":"2026-02-02","daysSinceLastAppearance":0,"averageCycle":24,"maxGan":74,"isDue":false,"hitDates":["2025-09-28","2025-10-24","2025-11-05","2026-01-18","2026-02-02"]}],"due":[{"number":"540","appearances":6,"lastDate":"2025-06-01","daysSinceLastAppearance":246,"averageCycle":49,"maxGan":75,"isDue":true,"hitDates":["2024-12-13","2025-01-01","2025-01-23","2025-03-19","2025-06-01"]},{"number":"915","appearances":12,"lastDate":"2025-06-05","daysSinceLastAppearance":242,"averageCycle":23,"maxGan":87,"isDue":true,"hitDates":["2025-03-04","2025-03-25","2025-04-07","2025-04-09","2025-06-05"]},{"number":"539","appearances":8,"lastDate":"2025-06-05","daysSinceLastAppearance":242,"averageCycle":36,"maxGan":81,"isDue":true,"hitDates":["2025-03-01","2025-03-21","2025-04-21","2025-05-30","2025-06-05"]},{"number":"144","appearances":10,"lastDate":"2025-06-19","daysSinceLastAppearance":228,"averageCycle":30,"maxGan":102,"isDue":true,"hitDates":["2025-04-07","2025-05-16","2025-06-12","2025-06-15","2025-06-19"]},{"number":"238","appearances":6,"lastDate":"2025-06-30","daysSinceLastAppearance":217,"averageCycle":52,"maxGan":150,"isDue":true,"hitDates":["2025-03-14","2025-04-11","2025-04-17","2025-05-10","2025-06-30"]},{"number":"730","appearances":6,"lastDate":"2025-07-07","daysSinceLastAppearance":210,"averageCycle":38,"maxGan":133,"isDue":true,"hitDates":["2025-05-13","2025-05-25","2025-06-03","2025-06-06","2025-07-07"]},{"number":"259","appearances":8,"lastDate":"2025-07-11","daysSinceLastAppearance":206,"averageCycle":41,"maxGan":117,"isDue":true,"hitDates":["2025-03-11","2025-05-12","2025-06-26","2025-06-28","2025-07-11"]},{"number":"576","appearances":8,"lastDate":"2025-07-14","daysSinceLastAppearance":203,"averageCycle":42,"maxGan":110,"isDue":true,"hitDates":["2024-12-04","2025-02-06","2025-05-27","2025-06-08","2025-07-14"]},{"number":"681","appearances":14,"lastDate":"2025-07-22","daysSinceLastAppearance":195,"averageCycle":22,"maxGan":81,"isDue":true,"hitDates":["2025-04-27","2025-05-08","2025-06-10","2025-07-21","2025-07-22"]},{"number":"366","appearances":6,"lastDate":"2025-07-24","daysSinceLastAppearance":193,"averageCycle":56,"maxGan":107,"isDue":true,"hitDates":["2025-02-01","2025-04-23","2025-06-22","2025-07-03","2025-07-24"]}]},"loto4Cang":{"top10":[{"number":"0761","appearances":8,"lastDate":"2025-10-07","daysSinceLastAppearance":118,"averageCycle":53,"maxGan":215,"isDue":true,"hitDates":["2025-01-29","2025-01-30","2025-01-31","2025-09-03","2025-10-07"]},{"number":"1673","appearances":8,"lastDate":"2025-08-30","daysSinceLastAppearance":156,"averageCycle":31,"maxGan":137,"isDue":true,"hitDates":["2025-01-30","2025-01-31","2025-03-15","2025-07-30","2025-08-30"]},{"number":"1978","appearances":7,"lastDate":"2025-08-20","daysSinceLastAppearance":166,"averageCycle":47,"maxGan":201,"isDue":true,"hitDates":["2025-01-28","2025-01-29","2025-01-30","2025-01-31","2025-08-20"]},{"number":"1409","appearances":7,"lastDate":"2025-06-30","daysSinceLastAppearance":217,"averageCycle":29,"maxGan":150,"isDue":true,"hitDates":["2025-01-28","2025-01-29","2025-01-30","2025-01-31","2025-06-30"]},{"number":"1776","appearances":7,"lastDate":"2026-01-07","daysSinceLastAppearance":26,"averageCycle":58,"maxGan":272,"isDue":false,"hitDates":["2025-01-29","2025-01-30","2025-01-31","2025-04-10","2026-01-07"]},{"number":"2768","appearances":7,"lastDate":"2025-11-13","daysSinceLastAppearance":81,"averageCycle":48,"maxGan":182,"isDue":true,"hitDates":["2025-01-29","2025-01-30","2025-01-31","2025-05-15","2025-11-13"]},{"number":"2248","appearances":7,"lastDate":"2026-01-17","daysSinceLastAppearance":16,"averageCycle":59,"maxGan":180,"isDue":false,"hitDates":["2025-01-29","2025-01-30","2025-01-31","2025-07-21","2026-01-17"]},{"number":"0032","appearances":7,"lastDate":"2025-12-17","daysSinceLastAppearance":47,"averageCycle":53,"maxGan":188,"isDue":false,"hitDates":["2025-04-11","2025-05-16","2025-11-20","2025-12-11","2025-12-17"]},{"number":"2944","appearances":6,"lastDate":"2026-01-31","daysSinceLastAppearance":2,"averageCycle":96,"maxGan":196,"isDue":false,"hitDates":["2025-04-20","2025-07-13","2025-08-24","2026-01-08","2026-01-31"]},{"number":"1875","appearances":6,"lastDate":"2025-10-13","daysSinceLastAppearance":112,"averageCycle":74,"maxGan":194,"isDue":true,"hitDates":["2024-12-02","2024-12-08","2025-03-17","2025-04-02","2025-10-13"]}],"due":[{"number":"2598","appearances":1,"lastDate":"2024-09-21","daysSinceLastAppearance":499,"averageCycle":500,"maxGan":499,"isDue":true,"hitDates":["2024-09-21"]},{"number":"8521","appearances":1,"lastDate":"2024-09-21","daysSinceLastAppearance":499,"averageCycle":500,"maxGan":499,"isDue":true,"hitDates":["2024-09-21"]},{"number":"6523","appearances":1,"lastDate":"2024-09-21","daysSinceLastAppearance":499,"averageCycle":500,"maxGan":499,"isDue":true,"hitDates":["2024-09-21"]},{"number":"7759","appearances":1,"lastDate":"2024-09-21","daysSinceLastAppearance":499,"averageCycle":500,"maxGan":499,"isDue":true,"hitDates":["2024-09-21"]},{"number":"8144","appearances":1,"lastDate":"2024-09-21","daysSinceLastAppearance":499,"averageCycle":500,"maxGan":499,"isDue":true,"hitDates":["2024-09-21"]},{"number":"8787","appearances":1,"lastDate":"2024-09-21","daysSinceLastAppearance":499,"averageCycle":500,"maxGan":499,"isDue":true,"hitDates":["2024-09-21"]},{"number":"6250","appearances":1,"lastDate":"2024-09-22","daysSinceLastAppearance":498,"averageCycle":500,"maxGan":498,"isDue":true,"hitDates":["2024-09-22"]},{"number":"6341","appearances":1,"lastDate":"2024-09-22","daysSinceLastAppearance":498,"averageCycle":500,"maxGan":498,"isDue":true,"hitDates":["2024-09-22"]},{"number":"0747","appearances":1,"lastDate":"2024-09-22","daysSinceLastAppearance":498,"averageCycle":500,"maxGan":498,"isDue":true,"hitDates":["2024-09-22"]},{"number":"1524","appearances":1,"lastDate":"2024-09-22","daysSinceLastAppearance":498,"averageCycle":500,"maxGan":498,"isDue":true,"hitDates":["2024-09-22"]}]},"overview":{"totalDays":500,"fromDate":"2024-09-21","toDate":"2026-02-02"}}}